[
    {
        "id": "NewB01",
        "name1": "OTHER SIDE 好想睡",
        "name2": "短篇漫畫集",
        "price": 270,
        "countInStock": 3,
        "image": "https://hinetcdn.waca.ec/uploads/shops/6750/products/d0/d06074f09c0f7b6c9c9b713c2ff7539a.jpg"
    },
    {
        "id": "NewB02",
        "name1": "流星雨",
        "name2": " ",
        "price": 200,
        "countInStock": 3,
        "image": "https://hinetcdn.waca.ec/uploads/shops/6750/products/ae/aef9694ac4c2074a1cbb0bc2eb8b29a7.jpg"
    },
    {
        "id": "NewB03",
        "name1": "親近大自然",
        "name2": " ",
        "price": 200,
        "countInStock": 5,
        "image": "https://hinetcdn.waca.ec/uploads/shops/6750/products/7f/7f72098c5007f457bfe439b11dbc0957.jpg"
    },
    {
        "id": "NewB04",
        "name1": "塑料人形安妮",
        "name2": " ",
        "price": 250,
        "countInStock": 5,
        "image": "https://hinetcdn.waca.ec/uploads/shops/6750/products/57/577abdf7195dc27c533fb7a27c27326c.jpg"
    },
    {
        "id": "NewB05",
        "name1": "不慌不忙",
        "name2": "電影宅通訊 vol.3",
        "price": 260,
        "countInStock": 5,
        "image": "https://hinetcdn.waca.ec/uploads/shops/6750/products/43/43bc4156da0751d1982174fb94f61b16.jpg"
    }
]